archeutils/__init__.py
archeutils/admin.py
archeutils/apps.py
archeutils/arche_rdf_views.py
archeutils/configs.py
archeutils/models.py
archeutils/tests.py
archeutils/urls.py
archeutils/utils.py
archeutils/migrations/__init__.py
acdh_django_archeutils-0.0.1.dist-info/LICENSE.txt
acdh_django_archeutils-0.0.1.dist-info/METADATA
acdh_django_archeutils-0.0.1.dist-info/WHEEL
acdh_django_archeutils-0.0.1.dist-info/top_level.txt
acdh_django_archeutils-0.0.1.dist-info/RECORD
