Metadata-Version: 2.1
Name: acdh-django-archeutils
Version: 0.0.1
Summary: Utility module to serialize a django-model into ARCHE-RDF.
Home-page: https://github.com/acdh-oeaw/acdh-django-archeutils
Author: Peter Andorfer
Author-email: peter.andorfer@oeaw.ac.at
License: MIT License
Platform: UNKNOWN
Classifier: Environment :: Web Environment
Classifier: Framework :: Django
Classifier: Framework :: Django :: 3.0
Classifier: Intended Audience :: Developers
Classifier: License :: OSI Approved :: MIT License
Classifier: Operating System :: OS Independent
Classifier: Programming Language :: Python
Classifier: Programming Language :: Python :: 3.6
Requires-Dist: Django (>=3.0)
Requires-Dist: rdflib (>=4.2.2)
